[
    {
        "cost":565,
        "voteCount":767,
        "reviewCount":767,
        "paymentMethods": {
            "card": "true",
            "cash": "true",
            "upi": "true"
        },
        "rating":4.6,
        "name":"Khana Khazana",
        "imageUrl":"https://b.zmtcdn.com/data/pictures/9/18568349/54d40362e31e3bdaef47857a4060b60e_o2_featured_v2.jpg"
    
    },
    {
        "cost":257,
        "voteCount":711,
        "reviewCount":432,
        "paymentMethods": {
            "card": "true",
            "cash": "false",
            "upi": "true"
        },
        "rating":4.1,
        "name":"WBFC",
        "imageUrl":"https://b.zmtcdn.com/data/pictures/1/23231/04339d7aa8d2880b2397fe08161f1635_o2_featured_v2.jpg?output-format=webp"

    },
    {
        "cost":228,
        "voteCount":223,
        "reviewCount":118,
        "paymentMethods": {
            "card": "false",
            "cash": "true",
            "upi": "true"
        },
        "rating":3.9,
        "name":"Al Baik Fast Food Corner",
        "imageUrl":"https://b.zmtcdn.com/data/pictures/6/18761176/ac0241893f90662ae294c580d014984c_o2_featured_v2.jpg?output-format=webp"

    },
    {
        "cost":288,
        "voteCount":434,
        "reviewCount":277,
        "paymentMethods": {
            "card": "true",
            "cash": "false",
            "upi": "true"
        },
        "rating":4.2,
        "name":"Bhukkad Gorilla",
        "imageUrl":"https://b.zmtcdn.com/data/pictures/9/19926839/5fffcaad8ab7f7ab5563feadd580b54d_o2_featured_v2.jpg?output-format=webp"

    },
    {
        "cost":332,
        "voteCount":4533,
        "reviewCount":466,
        "paymentMethods": {
            "card": "false",
            "cash": "true",
            "upi": "true"
        },
        "rating":4.2,
        "name":"New Paul Dhaba",
        "imageUrl":"https://b.zmtcdn.com/data/pictures/9/18561959/ee567c3cf31026c101a2df50060c310a_o2_featured_v2.jpg?output-format=webp"

    },
    {
        "cost":283,
        "voteCount":878,
        "reviewCount":566,
        "paymentMethods": {
            "card": "true",
            "cash": "false",
            "upi": "true"
        },
        "rating":4.4,
        "name":"Couch Potato",
        "imageUrl":"https://b.zmtcdn.com/data/pictures/9/18561959/ee567c3cf31026c101a2df50060c310a_o2_featured_v2.jpg?output-format=webp"

    },
    {
        "cost":320,
        "voteCount":433,
        "reviewCount":333,
        "paymentMethods": {
            "card": "false",
            "cash": "true",
            "upi": "true"
        },
        "rating":4.4,
        "name":"Zam Zam",
        "imageUrl":"https://b.zmtcdn.com/data/pictures/8/18965888/c48edbfd6a31a42e94948d726ce31c19_o2_featured_v2.jpg?output-format=webp"

    },
    {
        "cost":332,
        "voteCount":363,
        "reviewCount":444,
        "paymentMethods": {
            "card": "true",
            "cash": "false",
            "upi": "true"
        },
        "rating":4.7,
        "name":"Chaccha Jaan Biryani",
        "imageUrl":"https://b.zmtcdn.com/data/pictures/0/18461760/34f16ca887d95fc14b4aa5bb6f89e9b7_o2_featured_v2.jpg?output-format=webp"

    },
    {
        "cost":339,
        "voteCount":774,
        "reviewCount":442,
        "paymentMethods": {
            "card": "false",
            "cash": "true",
            "upi": "true"
        },
        "rating":4.2,
        "name":"Jai Hind Dhaba",
        "imageUrl":"https://b.zmtcdn.com/data/pictures/0/18461760/34f16ca887d95fc14b4aa5bb6f89e9b7_o2_featured_v2.jpg?output-format=webp"

    },
    {
        "cost":523,
        "voteCount":664,
        "reviewCount":723,
        "paymentMethods": {
            "card": "true",
            "cash": "false",
            "upi": "true"
        },
        "rating":4.3,
        "name":"Laziz Food Centre",
        "imageUrl":"https://b.zmtcdn.com/data/pictures/chains/3/18947213/0716b5947b013e6dc41f5defe0bb72e0_o2_featured_v2.jpg?output-format=webp"

    },
    {
        "cost":442,
        "voteCount":994,
        "reviewCount":520,
        "paymentMethods": {
            "card": "false",
            "cash": "true",
            "upi": "true"
        },
        "rating":3.9,
        "name":"Kabuliwala",
        "imageUrl":"https://b.zmtcdn.com/data/pictures/chains/3/18947213/0716b5947b013e6dc41f5defe0bb72e0_o2_featured_v2.jpg?output-format=webp"

    },
    {
        "cost":355,
        "voteCount":4334,
        "reviewCount":546,
        "paymentMethods": {
            "card": "true",
            "cash": "false",
            "upi": "true"
        },
        "rating":4.8,
        "name":"Chinese Dhaba",
        "imageUrl":"https://b.zmtcdn.com/data/pictures/5/25705/e2f6198514ae7714c201f8b95dd9a01c_o2_featured_v2.jpg"

    },
    {
        "cost":344,
        "voteCount":544,
        "reviewCount":645,
        "paymentMethods": {
            "card": "false",
            "cash": "true",
            "upi": "true"
        },
        "rating":4.5,
        "name":"Ayan Fast Food Center",
        "imageUrl":"https://b.zmtcdn.com/data/pictures/5/25705/e2f6198514ae7714c201f8b95dd9a01c_o2_featured_v2.jpg"

    },
    {
        "cost":455,
        "voteCount":655,
        "reviewCount":265,
        "paymentMethods": {
            "card": "true",
            "cash": "true",
            "upi": "true"
        },
        "rating":4.5,
        "name":"Anir's",
        "imageUrl":"https://b.zmtcdn.com/data/pictures/chains/5/21055/…477c94aa093c4628638286593bb9fa_o2_featured_v2.jpg"

    },
    {
        "cost":556,
        "voteCount":767,
        "reviewCount":768,
        "paymentMethods": {
            "card": "true",
            "cash": "true",
            "upi": "true"
        },
        "rating":768,
        "name":"Shiraz Golden Restaurant",
        "imageUrl":"https://b.zmtcdn.com/data/pictures/5/25705/e2f6198514ae7714c201f8b95dd9a01c_o2_featured_v2.jpg"

    },
    {
        "cost":878,
        "voteCount":7688,
        "reviewCount":677,
        "paymentMethods": {
            "card": "true",
            "cash": "true",
            "upi": "true"
        },
        "rating":4.6,
        "name":"Kankurgachi Dhaba",
        "imageUrl":"https://b.zmtcdn.com/data/pictures/0/18461760/34f16ca887d95fc14b4aa5bb6f89e9b7_o2_featured_v2.jpg"

    }
    
]